brooklyn_pkg/__init__.py
brooklyn_api_test-0.0.1.dist-info/LICENSE
brooklyn_api_test-0.0.1.dist-info/METADATA
brooklyn_api_test-0.0.1.dist-info/WHEEL
brooklyn_api_test-0.0.1.dist-info/top_level.txt
brooklyn_api_test-0.0.1.dist-info/RECORD
