Metadata-Version: 2.1
Name: brooklyn-api-test
Version: 0.0.1
Summary: package for the brooklyn board api
Home-page: https://github.com/ChiefCold2/BrooklynAPI.git
Author: Jonathan Hus
Author-email: husj015@gmail.com
License: UNKNOWN
Platform: UNKNOWN
Classifier: Programming Language :: Python :: 3
Classifier: License :: OSI Approved :: MIT License
Classifier: Operating System :: OS Independent
Requires-Python: >=3.6
